moban_jinja2_github/__init__.py
moban_jinja2_github/_version.py
moban_jinja2_github/contributors.py
moban_jinja2_github/issues.py
moban_jinja2_github-0.0.4.dist-info/LICENSE
moban_jinja2_github-0.0.4.dist-info/METADATA
moban_jinja2_github-0.0.4.dist-info/WHEEL
moban_jinja2_github-0.0.4.dist-info/top_level.txt
moban_jinja2_github-0.0.4.dist-info/RECORD
