Metadata-Version: 2.1
Name: moban-jinja2-github
Version: 0.0.4
Summary: Github specific filters, tests and globals
Home-page: https://github.com/moremoban/moban-jinja2-github
Author: chfw
Author-email: info@moremoban.org
License: newbsd
Download-URL: https://github.com/moremoban/moban-jinja2-github/archive/0.0.4.tar.gz
Keywords: python
Platform: UNKNOWN
Classifier: Topic :: Software Development :: Libraries
Classifier: Programming Language :: Python
Classifier: Intended Audience :: Developers
Classifier: Programming Language :: Python :: 2.6
Classifier: Programming Language :: Python :: 2.7
Classifier: Programming Language :: Python :: 3.3
Classifier: Programming Language :: Python :: 3.4
Classifier: Programming Language :: Python :: 3.5
Classifier: Programming Language :: Python :: 3.6
Classifier: Programming Language :: Python :: 3.7
Classifier: Programming Language :: Python :: 3.8
Requires-Dist: gease (>=0.0.7)
